dao_ai/__init__.py
dao_ai/catalog.py
dao_ai/cli.py
dao_ai/config.py
dao_ai/evaluation.py
dao_ai/graph.py
dao_ai/logging.py
dao_ai/messages.py
dao_ai/models.py
dao_ai/nodes.py
dao_ai/optimization.py
dao_ai/state.py
dao_ai/types.py
dao_ai/utils.py
dao_ai/vector_search.py
dao_ai/apps/__init__.py
dao_ai/apps/handlers.py
dao_ai/apps/model_serving.py
dao_ai/apps/resources.py
dao_ai/apps/server.py
dao_ai/genie/__init__.py
dao_ai/genie/core.py
dao_ai/genie/cache/__init__.py
dao_ai/genie/cache/base.py
dao_ai/genie/cache/core.py
dao_ai/genie/cache/in_memory_semantic.py
dao_ai/genie/cache/lru.py
dao_ai/genie/cache/semantic.py
dao_ai/hooks/__init__.py
dao_ai/hooks/core.py
dao_ai/memory/__init__.py
dao_ai/memory/base.py
dao_ai/memory/core.py
dao_ai/memory/databricks.py
dao_ai/memory/postgres.py
dao_ai/middleware/__init__.py
dao_ai/middleware/assertions.py
dao_ai/middleware/base.py
dao_ai/middleware/context_editing.py
dao_ai/middleware/core.py
dao_ai/middleware/guardrails.py
dao_ai/middleware/human_in_the_loop.py
dao_ai/middleware/message_validation.py
dao_ai/middleware/model_call_limit.py
dao_ai/middleware/model_retry.py
dao_ai/middleware/pii.py
dao_ai/middleware/summarization.py
dao_ai/middleware/tool_call_limit.py
dao_ai/middleware/tool_retry.py
dao_ai/middleware/tool_selector.py
dao_ai/orchestration/__init__.py
dao_ai/orchestration/core.py
dao_ai/orchestration/supervisor.py
dao_ai/orchestration/swarm.py
dao_ai/prompts/__init__.py
dao_ai/prompts/instructed_retriever_decomposition.yaml
dao_ai/prompts/instruction_reranker.yaml
dao_ai/prompts/router.yaml
dao_ai/prompts/verifier.yaml
dao_ai/providers/__init__.py
dao_ai/providers/base.py
dao_ai/providers/databricks.py
dao_ai/tools/__init__.py
dao_ai/tools/agent.py
dao_ai/tools/core.py
dao_ai/tools/email.py
dao_ai/tools/genie.py
dao_ai/tools/instructed_retriever.py
dao_ai/tools/instruction_reranker.py
dao_ai/tools/mcp.py
dao_ai/tools/memory.py
dao_ai/tools/python.py
dao_ai/tools/router.py
dao_ai/tools/search.py
dao_ai-0.1.19.dist-info/METADATA
dao_ai-0.1.19.dist-info/WHEEL
dao_ai-0.1.19.dist-info/entry_points.txt
dao_ai-0.1.19.dist-info/licenses/LICENSE
dao_ai-0.1.19.dist-info/RECORD
