Metadata-Version: 2.4
Name: dao-ai
Version: 0.1.19
Summary: DAO AI: A modular, multi-agent orchestration framework for complex AI workflows. Supports agent handoff, tool integration, and dynamic configuration via YAML.
Project-URL: Homepage, https://github.com/natefleming/dao-ai
Project-URL: Documentation, https://natefleming.github.io/dao-ai
Project-URL: Repository, https://github.com/natefleming/dao-ai
Project-URL: Issues, https://github.com/natefleming/dao-ai/issues
Project-URL: Changelog, https://github.com/natefleming/dao-ai/blob/main/CHANGELOG.md
Author-email: Nate Fleming <nate.fleming@databricks.com>, Nate Fleming <nate.fleming@gmail.com>
Maintainer-email: Nate Fleming <nate.fleming@databricks.com>
License: MIT
License-File: LICENSE
Keywords: agents,ai,databricks,langchain,langgraph,llm,multi-agent,orchestration,vector-search,workflow
Classifier: Development Status :: 3 - Alpha
Classifier: Intended Audience :: Developers
Classifier: Intended Audience :: Science/Research
Classifier: License :: OSI Approved :: MIT License
Classifier: Operating System :: OS Independent
Classifier: Programming Language :: Python :: 3
Classifier: Programming Language :: Python :: 3.11
Classifier: Programming Language :: Python :: 3.12
Classifier: Programming Language :: Python :: 3.13
Classifier: Topic :: Scientific/Engineering :: Artificial Intelligence
Classifier: Topic :: Software Development :: Libraries :: Python Modules
Classifier: Topic :: System :: Distributed Computing
Requires-Python: >=3.11
Requires-Dist: databricks-agents>=1.9.0
Requires-Dist: databricks-langchain[memory]>=0.13.0
Requires-Dist: databricks-mcp>=0.5.0
Requires-Dist: databricks-sdk[openai]>=0.77.0
Requires-Dist: ddgs>=9.10.0
Requires-Dist: dspy>=2.6.27
Requires-Dist: flashrank>=0.2.10
Requires-Dist: gepa>=0.0.22
Requires-Dist: grandalf>=0.8
Requires-Dist: langchain-community>=0.3.26
Requires-Dist: langchain-mcp-adapters>=0.2.1
Requires-Dist: langchain-tavily>=0.2.15
Requires-Dist: langchain>=1.2.0
Requires-Dist: langgraph-checkpoint-postgres>=3.0.2
Requires-Dist: langgraph>=1.0.5
Requires-Dist: langmem>=0.0.30
Requires-Dist: loguru>=0.7.3
Requires-Dist: mcp>=1.24.0
Requires-Dist: mlflow[databricks]>=3.8.1
Requires-Dist: nest-asyncio>=1.6.0
Requires-Dist: openevals>=0.1.3
Requires-Dist: openpyxl>=3.1.5
Requires-Dist: psycopg[binary,pool]>=3.3.2
Requires-Dist: pydantic>=2.12.5
Requires-Dist: python-dotenv>=1.2.1
Requires-Dist: pyyaml>=6.0.2
Requires-Dist: rich>=14.2.0
Requires-Dist: scipy>=1.14.0
Requires-Dist: sqlparse>=0.5.4
Requires-Dist: tomli>=2.3.0
Requires-Dist: unitycatalog-ai[databricks]>=0.3.2
Provides-Extra: databricks
Requires-Dist: databricks-connect>=16.0.0; extra == 'databricks'
Requires-Dist: databricks-vectorsearch>=0.63; extra == 'databricks'
Requires-Dist: pyspark>=3.5.0; extra == 'databricks'
Provides-Extra: dev
Requires-Dist: mypy>=1.19.1; extra == 'dev'
Requires-Dist: pre-commit>=4.5.1; extra == 'dev'
Requires-Dist: pytest>=9.0.2; extra == 'dev'
Requires-Dist: ruff>=0.14.9; extra == 'dev'
Provides-Extra: docs
Requires-Dist: mkdocs-material>=9.7.1; extra == 'docs'
Requires-Dist: mkdocs>=1.6.1; extra == 'docs'
Requires-Dist: mkdocstrings[python]>=1.0.0; extra == 'docs'
Provides-Extra: test
Requires-Dist: pytest-cov>=7.0.0; extra == 'test'
Requires-Dist: pytest-mock>=3.15.1; extra == 'test'
Requires-Dist: pytest-rerunfailures>=15.0; extra == 'test'
Requires-Dist: pytest-xdist>=3.6.1; extra == 'test'
Requires-Dist: pytest>=9.0.2; extra == 'test'
